jwt_hacker/__init__.py
jwt_hacker/decoder.py
jwt_hacker/gui.py
jwt_hacker-1.1.5.data/data/docs/LICENSE
jwt_hacker-1.1.5.data/data/docs/README.md
jwt_hacker-1.1.5.data/data/resources/icon.icns
jwt_hacker-1.1.5.data/data/resources/icon.ico
jwt_hacker-1.1.5.data/data/resources/icon.png
tests/__init__.py
tests/test_decoder.py
tests/test_integration.py
jwt_hacker-1.1.5.dist-info/LICENSE
jwt_hacker-1.1.5.dist-info/METADATA
jwt_hacker-1.1.5.dist-info/WHEEL
jwt_hacker-1.1.5.dist-info/entry_points.txt
jwt_hacker-1.1.5.dist-info/top_level.txt
jwt_hacker-1.1.5.dist-info/RECORD
