Metadata-Version: 2.2
Name: jwt-hacker
Version: 1.1.5
Summary: A futuristic tool to decode, analyze, and manipulate JWT tokens
Home-page: https://github.com/GreyNodeSecurity/JWT_Hacker
Author: Z3r0 S3c
Author-email: z3r0s3c@greynodesecurity.com
Maintainer: Grey Node Security
Maintainer-email: admin@greynodesecurity.com
License: MIT
Project-URL: Documentation, https://github.com/GreyNodeSecurity/JWT_Hacker/wiki
Project-URL: Source, https://github.com/GreyNodeSecurity/JWT_Hacker
Project-URL: Website, https://greynodesecurity.com
Project-URL: Tracker, https://github.com/GreyNodeSecurity/JWT_Hacker/issues
Keywords: JWT decoding hacking security tool analysis manipulation
Classifier: Development Status :: 4 - Beta
Classifier: Intended Audience :: Developers
Classifier: Intended Audience :: Information Technology
Classifier: Topic :: Security
Classifier: Topic :: Software Development :: Libraries
Classifier: License :: OSI Approved :: MIT License
Classifier: Programming Language :: Python :: 3
Classifier: Programming Language :: Python :: 3.8
Classifier: Programming Language :: Python :: 3.9
Classifier: Programming Language :: Python :: 3.10
Classifier: Programming Language :: Python :: 3.11
Classifier: Operating System :: OS Independent
Requires-Python: >=3.6
License-File: LICENSE
Requires-Dist: pycryptodome>=3.11.0
Requires-Dist: pyjwt>=2.4.0
Requires-Dist: cryptography>=39.0.0
Requires-Dist: requests>=2.20.0
Requires-Dist: tkintertable
Requires-Dist: pytest>=7.0.0
Requires-Dist: datetime
Provides-Extra: dev
Requires-Dist: pytest; extra == "dev"
Requires-Dist: black; extra == "dev"
Requires-Dist: flake8; extra == "dev"
Dynamic: author
Dynamic: author-email
Dynamic: classifier
Dynamic: description
Dynamic: description-content-type
Dynamic: home-page
Dynamic: keywords
Dynamic: license
Dynamic: maintainer
Dynamic: maintainer-email
Dynamic: project-url
Dynamic: provides-extra
Dynamic: requires-dist
Dynamic: requires-python
Dynamic: summary
